README.md
pyproject.toml
setup.py
./proxycurl_py_test/__init__.py
./proxycurl_py_test/config.py
./proxycurl_py_test/models.py
./proxycurl_py_test/asyncio/__init__.py
./proxycurl_py_test/asyncio/base.py
./proxycurl_py_test/asyncio/library.py
./proxycurl_py_test/gevent/__init__.py
./proxycurl_py_test/gevent/base.py
./proxycurl_py_test/gevent/library.py
./proxycurl_py_test/twisted/__init__.py
./proxycurl_py_test/twisted/base.py
./proxycurl_py_test/twisted/library.py
proxycurl_py_test_2.egg-info/PKG-INFO
proxycurl_py_test_2.egg-info/SOURCES.txt
proxycurl_py_test_2.egg-info/dependency_links.txt
proxycurl_py_test_2.egg-info/requires.txt
proxycurl_py_test_2.egg-info/top_level.txt